minipresto/__init__.py
minipresto/cli.py
minipresto/components.py
minipresto/errors.py
minipresto/settings.py
minipresto/utils.py
minipresto/cmd/__init__.py
minipresto/cmd/cmd_config.py
minipresto/cmd/cmd_down.py
minipresto/cmd/cmd_lib_install.py
minipresto/cmd/cmd_modules.py
minipresto/cmd/cmd_provision.py
minipresto/cmd/cmd_remove.py
minipresto/cmd/cmd_snapshot.py
minipresto/cmd/cmd_version.py
minipresto-1.0.2.dist-info/METADATA
minipresto-1.0.2.dist-info/WHEEL
minipresto-1.0.2.dist-info/entry_points.txt
minipresto-1.0.2.dist-info/top_level.txt
minipresto-1.0.2.dist-info/RECORD
