Metadata-Version: 2.1
Name: minipresto
Version: 1.0.2
Summary: A command line tool that makes it easy to run modular Presto environments locally.
Home-page: https://github.com/jefflester/minipresto
Author: Jeff Lester
Author-email: jeff.lester.dev@gmail.com
License: Apache-2.0
Platform: UNKNOWN
Classifier: Programming Language :: Python :: 3
Classifier: License :: OSI Approved :: Apache Software License
Classifier: Operating System :: OS Independent
Requires-Python: >=3.8
Requires-Dist: click (==7.1.2)
Requires-Dist: colorama
Requires-Dist: docker (==5.0.0)
Requires-Dist: PyYAML
